{
  "buildDate": "2025-06-19T02:00:45.680Z",
  "nodeVersion": "v18.12.1",
  "platform": "win32",
  "arch": "x64",
  "commitHash": "b522eb59ac6f31f47094566be3f4b889eb34c42e",
  "commitHashShort": "b522eb5",
  "branch": "main",
  "commitDate": "2025-06-19T01:38:36.000Z",
  "commitMessage": "Migrate navigation demo functionality from /nav-demo to /home route",
  "isDirty": true,
  "repoUrl": "https://github.com/lilzenon/kutt.git",
  "githubUrl": "https://github.com/lilzenon/kutt",
  "commitUrl": "https://github.com/lilzenon/kutt/commit/b522eb59ac6f31f47094566be3f4b889eb34c42e",
  "displayText": "main@b522eb5*",
  "environment": "development"
}